qtregpy/__init__.py
qtregpy/compute.py
qtregpy/cvxpy_socket.py
qtregpy/gtreg_utils.py
qtregpy/ingestion.py
qtregpy-0.1.2.dist-info/LICENSE.txt
qtregpy-0.1.2.dist-info/METADATA
qtregpy-0.1.2.dist-info/WHEEL
qtregpy-0.1.2.dist-info/top_level.txt
qtregpy-0.1.2.dist-info/RECORD
