Metadata-Version: 2.1
Name: qtregpy
Version: 0.1.2
Summary: A Python package to implement the Quantile Transformation Regression.
Home-page: https://github.com/diego-lda/qtregpy
Download-URL: https://github.com/diego-lda/qtregpy/archive/refs/tags/0.1.2.tar.gz
Author: Sami Stouli, Richard Spady, Xiaoran Liang, Diego Lara
Author-email: s.stouli@bristol.ac.uk, rspady@jhu.edu, x.liang2@exeter.ac.uk, diegolaradeandres@gmail.com
License: MIT
Keywords: DISTRIBUTION,DENSITY,ECONOMETRICS,ESTIMATION
Classifier: License :: OSI Approved :: MIT License
Classifier: Programming Language :: Python :: 3
Classifier: Programming Language :: Python :: 3.11
Requires: cvxpy
Requires: ecos
Requires: iniconfig
Requires: numpy
Requires: osqp
Requires: packaging
Requires: pluggy
Requires: pytest
Requires: qdldl
Requires: scipy
Requires: scs
Requires-Python: >=3.11
License-File: LICENSE.txt
